[
  {
    "inputs": [
      {
        "internalType": "address",
        "name": "_gateKeeper",
        "type": "address"
      }
    ],
    "stateMutability": "nonpayable",
    "type": "constructor"
  },
  {
    "anonymous": false,
    "inputs": [
      {
        "indexed": false,
        "internalType": "address",
        "name": "originalTarget",
        "type": "address"
      },
      {
        "indexed": false,
        "internalType": "address",
        "name": "newTarget",
        "type": "address"
      }
    ],
    "name": "TargetChanged",
    "type": "event"
  },
  {
    "inputs": [],
    "name": "UPGRADE_CONTRACT",
    "outputs": [
      {
        "internalType": "bytes32",
        "name": "",
        "type": "bytes32"
      }
    ],
    "stateMutability": "view",
    "type": "function"
  },
  {
    "inputs": [],
    "name": "_target",
    "outputs": [
      {
        "internalType": "address",
        "name": "",
        "type": "address"
      }
    ],
    "stateMutability": "view",
    "type": "function"
  },
  {
    "inputs": [],
    "name": "_value",
    "outputs": [
      {
        "internalType": "uint256",
        "name": "",
        "type": "uint256"
      }
    ],
    "stateMutability": "view",
    "type": "function"
  },
  {
    "inputs": [],
    "name": "_value2",
    "outputs": [
      {
        "internalType": "uint256",
        "name": "",
        "type": "uint256"
      }
    ],
    "stateMutability": "view",
    "type": "function"
  },
  {
    "inputs": [],
    "name": "gateKeeper",
    "outputs": [
      {
        "internalType": "contract GateKeeper",
        "name": "",
        "type": "address"
      }
    ],
    "stateMutability": "view",
    "type": "function"
  },
  {
    "inputs": [],
    "name": "getUint",
    "outputs": [
      {
        "internalType": "uint256",
        "name": "",
        "type": "uint256"
      }
    ],
    "stateMutability": "view",
    "type": "function"
  },
  {
    "inputs": [],
    "name": "getValues",
    "outputs": [
      {
        "internalType": "uint256",
        "name": "v1",
        "type": "uint256"
      },
      {
        "internalType": "uint256",
        "name": "v2",
        "type": "uint256"
      }
    ],
    "stateMutability": "view",
    "type": "function"
  },
  {
    "inputs": [
      {
        "internalType": "uint256",
        "name": "value",
        "type": "uint256"
      }
    ],
    "name": "setUint",
    "outputs": [],
    "stateMutability": "nonpayable",
    "type": "function"
  }
]
